{
    "initial_capital": 50000.0,
    "transactions": [
        {
            "recorder": "Wasabi",
            "buyer": "Dar_111",
            "item": "CDK MM",
            "cost": 18.0,
            "price": 30.0,
            "qty": 98,
            "total": 2940.0,
            "profit": 1176.0,
            "status": "โอนแล้ว"
        },
        {
            "recorder": "Wasabi",
            "buyer": "leowinmorsai\n",
            "item": "V4 T10 CDK",
            "cost": 32.0,
            "price": 45.0,
            "qty": 10,
            "total": 450.0,
            "profit": 130.0,
            "status": "โอนแล้ว"
        },
        {
            "recorder": "Wasabi",
            "buyer": "Apisit",
            "item": "V4 T10 CDK",
            "cost": 32.0,
            "price": 45.0,
            "qty": 607,
            "total": 27315.0,
            "profit": 7891.0,
            "status": "โอนแล้ว"
        },
        {
            "recorder": "Wasabi",
            "buyer": "Apisit",
            "item": "V4 T10 CDK",
            "cost": 32.0,
            "price": 50.0,
            "qty": 150,
            "total": 7500.0,
            "profit": 2700.0,
            "status": "โอนแล้ว"
        },
        {
            "recorder": "Wasabi",
            "buyer": "Nooker",
            "item": "V4 T10 CDK",
            "cost": 32.0,
            "price": 50.0,
            "qty": 180,
            "total": 9000.0,
            "profit": 3240.0,
            "status": "โอนแล้ว"
        },
        {
            "recorder": "Wasabi",
            "buyer": "Nooker",
            "item": "V4 T10 CDK ผลโหด",
            "cost": 32.0,
            "price": 60.0,
            "qty": 50,
            "total": 3000.0,
            "profit": 1400.0,
            "status": "โอนแล้ว"
        },
        {
            "recorder": "Wasabi",
            "buyer": "pk",
            "item": "V4 T10 CDK",
            "cost": 32.0,
            "price": 65.0,
            "qty": 70,
            "total": 4550.0,
            "profit": 2310.0,
            "status": "โอนแล้ว"
        },
        {
            "recorder": "Wasabi",
            "buyer": "pk",
            "item": "V4 T10 CDK ผลโหด",
            "cost": 32.0,
            "price": 75.0,
            "qty": 270,
            "total": 20250.0,
            "profit": 11610.0,
            "status": "โอนแล้ว"
        },
        {
            "recorder": "Wasabi",
            "buyer": "Yotin",
            "item": "V4 T10 CDK",
            "cost": 32.0,
            "price": 50.0,
            "qty": 127,
            "total": 6350.0,
            "profit": 2286.0,
            "status": "โอนแล้ว"
        },
        {
            "recorder": "Wasabi",
            "buyer": "Yotin",
            "item": "V4 T10 CDK",
            "cost": 32.0,
            "price": 50.0,
            "qty": 180,
            "total": 9000.0,
            "profit": 3240.0,
            "status": "โอนแล้ว"
        },
        {
            "recorder": "rezex",
            "buyer": "Dar_111",
            "item": "CDK MM",
            "cost": 18.0,
            "price": 30.0,
            "qty": 10,
            "total": 300.0,
            "profit": 120.0,
            "status": "ยังไม่โอน"
        }
    ]
}